renga/__init__.py
renga/client.py
renga/conftest.py
renga/errors.py
renga/notebook.py
renga/version.py
renga/api/__init__.py
renga/api/authorization.py
renga/api/client.py
renga/api/deployer.py
renga/api/explorer.py
renga/api/projects.py
renga/api/storage.py
renga/cli/__init__.py
renga/cli/_client.py
renga/cli/_config.py
renga/cli/_group.py
renga/cli/_options.py
renga/cli/_version.py
renga/cli/add.py
renga/cli/deployments.py
renga/cli/endpoint.py
renga/cli/env.py
renga/cli/init.py
renga/cli/io.py
renga/cli/login.py
renga/cli/notebooks.py
renga/models/__init__.py
renga/models/_datastructures.py
renga/models/_tabulate.py
renga/models/deployer.py
renga/models/projects.py
renga/models/storage.py
renga-0.1.0.dev20171123.dist-info/DESCRIPTION.rst
renga-0.1.0.dev20171123.dist-info/METADATA
renga-0.1.0.dev20171123.dist-info/RECORD
renga-0.1.0.dev20171123.dist-info/WHEEL
renga-0.1.0.dev20171123.dist-info/entry_points.txt
renga-0.1.0.dev20171123.dist-info/metadata.json
renga-0.1.0.dev20171123.dist-info/top_level.txt
