Metadata-Version: 2.0
Name: renga
Version: 0.1.0.dev20171123
Summary: Python SDK and CLI for the Renga platform.
Home-page: https://github.com/SwissDataScienceCenter/renga-python
Author: Swiss Data Science Center
Author-email: contact@datascience.ch
License: Apache License 2.0
Keywords: Renga CLI
Platform: any
Classifier: Environment :: Web Environment
Classifier: Intended Audience :: Developers
Classifier: License :: OSI Approved :: Apache Software License
Classifier: Operating System :: OS Independent
Classifier: Programming Language :: Python
Classifier: Topic :: Internet :: WWW/HTTP :: Dynamic Content
Classifier: Topic :: Software Development :: Libraries :: Python Modules
Classifier: Programming Language :: Python :: 3
Classifier: Programming Language :: Python :: 3.6
Classifier: Development Status :: 1 - Planning
Requires-Dist: PyYAML (>=3.12)
Requires-Dist: click (>=6.7)
Requires-Dist: click-plugins (>=1.0.3)
Requires-Dist: requests (>=2.18.4)
Requires-Dist: requests-oauthlib (>=0.8.0)
Requires-Dist: tabulate (>=0.7.7)
Requires-Dist: werkzeug (>=0.12)
Requires-Dist: pathlib2 (>=2.3.0); python_version<"3.6"
Provides-Extra: all
Requires-Dist: Sphinx (>=1.6.3); extra == 'all'
Requires-Dist: Sphinx (>=1.6.3); extra == 'all'
Requires-Dist: check-manifest (>=0.25); extra == 'all'
Requires-Dist: check-manifest (>=0.25); extra == 'all'
Requires-Dist: coverage (>=4.0); extra == 'all'
Requires-Dist: coverage (>=4.0); extra == 'all'
Requires-Dist: isort (>=4.2.2); extra == 'all'
Requires-Dist: isort (>=4.2.2); extra == 'all'
Requires-Dist: jupyter (>=1.0.0); extra == 'all'
Requires-Dist: jupyter (>=1.0.0); extra == 'all'
Requires-Dist: pydocstyle (>=1.0.0); extra == 'all'
Requires-Dist: pydocstyle (>=1.0.0); extra == 'all'
Requires-Dist: pytest (>=3.2.1); extra == 'all'
Requires-Dist: pytest (>=3.2.1); extra == 'all'
Requires-Dist: pytest-cache (>=1.0); extra == 'all'
Requires-Dist: pytest-cache (>=1.0); extra == 'all'
Requires-Dist: pytest-cov (>=2.5.1); extra == 'all'
Requires-Dist: pytest-cov (>=2.5.1); extra == 'all'
Requires-Dist: pytest-pep8 (>=1.0.6); extra == 'all'
Requires-Dist: pytest-pep8 (>=1.0.6); extra == 'all'
Requires-Dist: renga-sphinx-theme (>=0.1.0); extra == 'all'
Requires-Dist: renga-sphinx-theme (>=0.1.0); extra == 'all'
Requires-Dist: responses (>=0.7.0); extra == 'all'
Requires-Dist: responses (>=0.7.0); extra == 'all'
Provides-Extra: docs
Requires-Dist: Sphinx (>=1.6.3); extra == 'docs'
Provides-Extra: notebook
Requires-Dist: jupyter (>=1.0.0); extra == 'notebook'
Provides-Extra: tests
Requires-Dist: check-manifest (>=0.25); extra == 'tests'
Requires-Dist: coverage (>=4.0); extra == 'tests'
Requires-Dist: isort (>=4.2.2); extra == 'tests'
Requires-Dist: pydocstyle (>=1.0.0); extra == 'tests'
Requires-Dist: pytest (>=3.2.1); extra == 'tests'
Requires-Dist: pytest-cache (>=1.0); extra == 'tests'
Requires-Dist: pytest-cov (>=2.5.1); extra == 'tests'
Requires-Dist: pytest-pep8 (>=1.0.6); extra == 'tests'
Requires-Dist: renga-sphinx-theme (>=0.1.0); extra == 'tests'
Requires-Dist: responses (>=0.7.0); extra == 'tests'
